snakegram/__init__.py
snakegram/_rust.cpython-310-x86_64-linux-gnu.so
snakegram/about.py
snakegram/alias.py
snakegram/enums.py
snakegram/filters.py
snakegram/helpers.py
snakegram/models.py
snakegram/py.typed
snakegram/core/__init__.py
snakegram/core/handlers.py
snakegram/core/telegram.py
snakegram/core/_system/__init__.py
snakegram/core/_system/tracker.py
snakegram/core/internal/__init__.py
snakegram/core/internal/cache_entities.py
snakegram/core/internal/downloader.py
snakegram/core/internal/update_state.py
snakegram/core/internal/uploader.py
snakegram/core/methods/__init__.py
snakegram/core/methods/auth.py
snakegram/core/methods/common.py
snakegram/core/methods/messages.py
snakegram/core/methods/updates.py
snakegram/core/methods/upload.py
snakegram/crypto/__init__.py
snakegram/crypto/aes.py
snakegram/crypto/auth_key.py
snakegram/crypto/password.py
snakegram/crypto/public_key.py
snakegram/crypto/utils.py
snakegram/errors/__init__.py
snakegram/errors/bad_message_errors.py
snakegram/errors/base_rpc_errors.py
snakegram/errors/common.py
snakegram/errors/rpc_errors/__init__.py
snakegram/errors/rpc_errors/bad_request_errors.py
snakegram/errors/rpc_errors/flood_errors.py
snakegram/errors/rpc_errors/forbidden_errors.py
snakegram/errors/rpc_errors/internal_errors.py
snakegram/errors/rpc_errors/not_acceptable_errors.py
snakegram/errors/rpc_errors/not_found_errors.py
snakegram/errors/rpc_errors/see_other_errors.py
snakegram/errors/rpc_errors/timedout_errors.py
snakegram/errors/rpc_errors/unauthorized_errors.py
snakegram/gadgets/byteutils.py
snakegram/gadgets/http.py
snakegram/gadgets/tlobject.py
snakegram/gadgets/utils.py
snakegram/gadgets/filter/__init__.py
snakegram/gadgets/filter/base.py
snakegram/gadgets/filter/proxy_filter.py
snakegram/gadgets/parser/__init__.py
snakegram/gadgets/parser/base.py
snakegram/gadgets/parser/html.py
snakegram/gadgets/parser/markdown.py
snakegram/network/__init__.py
snakegram-1.0.0.dev8.dist-info/METADATA
snakegram-1.0.0.dev8.dist-info/WHEEL
snakegram-1.0.0.dev8.dist-info/top_level.txt
snakegram-1.0.0.dev8.dist-info/RECORD
snakegram-1.0.0.dev8.dist-info/licenses/LICENSE
